setup.py
pydatagen/__init__.py
pydatagen/connectedgraph.py
pydatagen/randgraph.py
pydatagen/randlist.py
pydatagen/randtree.py
pydatagen.egg-info/PKG-INFO
pydatagen.egg-info/SOURCES.txt
pydatagen.egg-info/dependency_links.txt
pydatagen.egg-info/not-zip-safe
pydatagen.egg-info/top_level.txt