Metadata-Version: 1.0
Name: pydatagen
Version: 0.1
Summary: random data generator package
Home-page: https://github.com/prrateekk/pydatagen
Author: Prateek Agarwal
Author-email: prrateekk@hotmail.com
License: UNKNOWN
Platform: UNKNOWN
